VERSION
pfl/__init__.py
pfl/aggregate/__init__.py
pfl/aggregate/base.py
pfl/aggregate/data_transport.py
pfl/aggregate/simulate.py
pfl/aggregate/weighting.py
pfl/algorithm/__init__.py
pfl/algorithm/algorithm_utils.py
pfl/algorithm/base.py
pfl/algorithm/expectation_maximization_gmm.py
pfl/algorithm/federated_averaging.py
pfl/algorithm/fedprox.py
pfl/algorithm/reptile.py
pfl/algorithm/scaffold.py
pfl/callback/__init__.py
pfl/callback/aggregate_metrics_to_disk.py
pfl/callback/base.py
pfl/callback/central_evaluation.py
pfl/callback/checkpoint.py
pfl/callback/convergence.py
pfl/callback/early_stopping.py
pfl/callback/profiler.py
pfl/callback/restore_training.py
pfl/callback/stopwatch.py
pfl/callback/tensorboard.py
pfl/callback/track_best_overall_metrics.py
pfl/callback/wandb.py
pfl/common_types.py
pfl/context.py
pfl/data/__init__.py
pfl/data/dataset.py
pfl/data/federated_dataset.py
pfl/data/partition.py
pfl/data/pytorch.py
pfl/data/sampling.py
pfl/data/tensorflow.py
pfl/data/user_state.py
pfl/exception.py
pfl/hyperparam/__init__.py
pfl/hyperparam/base.py
pfl/internal/__init__.py
pfl/internal/bisect.py
pfl/internal/bridge/__init__.py
pfl/internal/bridge/base.py
pfl/internal/bridge/factory.py
pfl/internal/bridge/mlx/__init__.py
pfl/internal/bridge/mlx/sgd.py
pfl/internal/bridge/numpy/__init__.py
pfl/internal/bridge/numpy/common.py
pfl/internal/bridge/pytorch/__init__.py
pfl/internal/bridge/pytorch/common.py
pfl/internal/bridge/pytorch/ftrl.py
pfl/internal/bridge/pytorch/proximal.py
pfl/internal/bridge/pytorch/scaffold.py
pfl/internal/bridge/pytorch/sgd.py
pfl/internal/bridge/pytorch/utils.py
pfl/internal/bridge/tensorflow/__init__.py
pfl/internal/bridge/tensorflow/common.py
pfl/internal/bridge/tensorflow/ftrl.py
pfl/internal/bridge/tensorflow/proximal.py
pfl/internal/bridge/tensorflow/sgd.py
pfl/internal/distribution/__init__.py
pfl/internal/distribution/diagonal_gaussian.py
pfl/internal/distribution/distribution.py
pfl/internal/distribution/log_float.py
pfl-0.5.0.dist-info/LICENSE
pfl-0.5.0.dist-info/METADATA
pfl-0.5.0.dist-info/WHEEL
pfl-0.5.0.dist-info/RECORD
