Metadata-Version: 2.1
Name: pfl
Version: 0.5.0
Summary: Simulation framework for Private Federated Learning
Home-page: https://github.com/apple/pfl-research
Author: Apple
Requires-Python: >=3.10,<3.13
Classifier: Programming Language :: Python :: 3
Classifier: Programming Language :: Python :: 3.10
Classifier: Programming Language :: Python :: 3.11
Provides-Extra: mlx
Provides-Extra: pytorch
Provides-Extra: tf
Provides-Extra: trees
Requires-Dist: dp-accounting (>=0.4,<0.6)
Requires-Dist: mlx (>=0.15.2,<0.30) ; extra == "mlx"
Requires-Dist: multiprocess (>=0.70.15,<0.71)
Requires-Dist: numpy (>=1.21,<3)
Requires-Dist: packaging (>=24.0,<26)
Requires-Dist: prv-accountant (>=0.2.0,<0.3.0)
Requires-Dist: scikit-learn (>=1.0.2,<2) ; extra == "trees"
Requires-Dist: scipy (>=1.7.3)
Requires-Dist: tensorflow (>=2.16.1,<3.0.0) ; extra == "tf"
Requires-Dist: tensorflow-probability[tf] (>=0.24) ; extra == "tf"
Requires-Dist: torch (>=2.0.1,<3.0.0) ; (sys_platform == "darwin") and (extra == "pytorch")
Requires-Dist: torch (>=2.0.1,<3.0.0) ; (sys_platform == "linux") and (extra == "pytorch")
Requires-Dist: wheel (>=0.41.2,<0.46)
Requires-Dist: xgboost (>=1.4.2,<4) ; extra == "trees"
Project-URL: Repository, https://github.com/apple/pfl-research
